{"word2index": {"\u0111\u1ed3ng": 2, "th\u1eddi": 3, ",": 4, "b\u1ec7nh": 5, "vi\u1ec7n": 6, "ti\u1ebfp": 7, "t\u1ee5c": 8, "th\u1ef1c": 9, "hi\u1ec7n": 10, "c\u00e1c": 11, "bi\u1ec7n": 12, "ph\u00e1p": 13, "ph\u00f2ng": 14, "ch\u1ed1ng": 15, "d\u1ecbch": 16, "covid": 17, "-": 18, "19": 19, "theo": 20, "h\u01b0\u1edbng": 21, "d\u1eabn": 22, "c\u1ee7a": 23, "b\u1ed9": 24, "y": 25, "t\u1ebf": 26, ".": 27, "\"": 28, "s\u1ed1": 29, "c\u00f3": 30, "th\u1ec3": 31, "nh\u1eadn": 32, "nh\u00e2n": 33, "b\u1ecb": 34, "s\u1ed1t": 35, "cao": 36, "v\u00e0": 37, "kh\u00f3": 38, "th\u1edf": 39, "\u0111ang": 40, "gi\u1ea3m": 41, "d\u1ea7n": 42, "th\u00f4ng": 43, "c\u00e1o": 44, "\u0111o\u1ea1n": 45, "c\u1ea3nh": 46, "b\u00e1o": 47, "nh\u1eefng": 48, "n\u00e0y": 49, "thay": 50, "v\u00e0o": 51, "\u0111\u00f3": 52, "\u0111\u01b0\u1ee3c": 53, "chuy\u1ec3n": 54, "t\u1edbi": 55, "kh\u00e1m": 56, "kh\u1ea9n": 57, "c\u1ea5p": 58, "khi\u1ebfn": 59, "m\u1eafc": 60, "hi\u1ec3m": 61, "ngh\u00e8o": 62, "kh\u00e1c": 63, "kh\u00f4ng": 64, "c\u01a1": 65, "h\u1ed9i": 66, "\u0111i\u1ec1u": 67, "tr\u1ecb": 68, "ngo\u00e0i": 69, "ra": 70, "ng\u01b0\u1eddi": 71, "x\u00fac": 72, "gi\u00e1n": 73, "(": 74, "\u0111\u00e3": 75, "g\u1eb7p": 76, "g\u1ea7n": 77, "v\u1edbi": 78, ")": 79, "l\u1eadp": 80, "danh": 81, "s\u00e1ch": 82, "y\u00eau": 83, "c\u1ea7u": 84, "c\u00e1ch": 85, "ly": 86, "t\u1ea1i": 87, "n\u01a1i": 88, "\u1edf": 89, "b\u00e0": 90, "khi": 91, "tr\u1edf": 92, "v\u1ec1": 93, "qu\u00e1": 94, "doha": 95, "qatar": 96, "\u0111\u00e1p": 97, "xu\u1ed1ng": 98, "t\u00e2n": 99, "s\u01a1n": 100, "nh\u1ea5t": 101, "s\u00e1ng": 102, "2/3": 103, "c\u00f9ng": 104, "75": 105, "h\u00e0nh": 106, "kh\u00e1ch": 107, "trong": 108, "55": 109, "n\u01b0\u1edbc": 110, "523": 111, "ch\u1ed3ng": 112, "l\u00e0": 113, "522": 114, "67": 115, "tu\u1ed5i": 116, "ghi": 117, "nhi\u1ec5m": 118, "ncov": 119, "h\u00f4m": 120, "31/7": 121, "tr\u01b0\u1eddng": 122, "h\u1ee3p": 123, "188": 124, "l.t.h.": 125, "tin": 126, "t\u1eeb": 127, "quan": 128, "\u0111\u1ecba": 129, "ph\u01b0\u01a1ng": 130, "nh\u00e0": 131, "ng\u00e0y": 132, "14": 133, "4": 134, "ch\u1ec9": 135, "con": 136, "\u0111\u00e2y": 137, "ph\u1ea3i": 138, "t\u00e1i": 139, "m\u00e0": 140, "do": 141, "virus": 142, "y\u1ebfu": 143, "\u0111i\u1ec3m": 144, "l\u1ea5y": 145, "m\u1eabu": 146, "l\u1ea7n": 147, "tr\u01b0\u1edbc": 148, "ho\u1eb7c": 149, "v\u1ecb": 150, "tr\u00ed": 151, "\u0111\u1ebfn": 152, "\u00e2m": 153, "t\u00ednh": 154, "gi\u1ea3": 155, "ri\u00eang": 156, "91": 157, "phi": 158, "c\u00f4ng": 159, "anh": 160, "ng\u1ee5": 161, "qu\u1eadn": 162, "2": 163, "tp.": 164, "hcm": 165, "li\u00ean": 166, "\u1ed5": 167, "qu\u00e1n": 168, "bar": 169, "buddha": 170, "c\u1eadp": 171, "nh\u1eadt": 172, "10": 173, "cho": 174, "bi\u1ebft": 175, "di\u1ec5n": 176, "bi\u1ebfn": 177, "x\u1ea5u": 178, "h\u01a1n": 179, "nh\u01b0ng": 180, "c\u0169ng": 181, "ch\u01b0a": 182, "d\u1ea5u": 183, "hi\u1ec7u": 184, "h\u1ed3i": 185, "ph\u1ee5c": 186, "x\u00e9t": 187, "nghi\u1ec7m": 188, "3": 189, "k\u1ebft": 190, "qu\u1ea3": 191, "21": 192, "23": 193, "8": 194, "th\u00e2n": 195, "x\u00e1c": 196, "\u0111\u1ecbnh": 197, "vi\u1ec7t": 198, "nam": 199, "chi\u1ec1u": 200, "22": 201, "d\u00f5i": 202, "qua": 203, "hai": 204, "t\u1eed": 205, "vong": 206, "n\u1ec1n": 207, "suy": 208, "th\u1eadn": 209, "m\u1ea1n": 210, "8h": 211, "1": 212, "861": 213, "ch\u1edf": 214, "g\u00e1i": 215, "\u0111a": 216, "khoa": 217, "b\u00e1c": 218, "s\u0129": 219, "ho\u00e0ng": 220, "\u0111\u1ee9c": 221, "d\u0169ng": 222, "16": 223, "18": 224, "b": 225, "\u0111\u01b0\u1eddng": 226, "l\u00ea": 227, "du\u1ea9n": 228, "tp": 229, "\u0111\u00f4ng": 230, "h\u00e0": 231, "c\u1ea3": 232, "\u0111\u1ec1u": 233, "thu\u1ed9c": 234, "di\u1ec7n": 235, "s\u00e0ng": 236, "l\u1ecdc": 237, "ph\u1ea9m": 238, "11/4": 239, "d\u01b0\u01a1ng": 240, "13/4": 241, "nhi\u1ec7t": 242, "\u0111\u1edbi": 243, "trung": 244, "\u01b0\u01a1ng": 245, "s\u1edf": 246, "11": 247, "tr\u00ean": 248, "b\u00e0n": 249, "t\u1ec9nh": 250, "qu\u1ea3ng": 251, "ninh": 252, "ph\u00e1t": 253, "th\u00eam": 254, "ca": 255, "du": 256, "\u0111i": 257, "chuy\u1ebfn": 258, "bay": 259, "vn0054": 260, "th\u1ee9": 261, "17": 262, "gd": 263, "\u0111t": 264, "tri\u1ec7t": 265, "t\u1ea5t": 266, "th\u00ed": 267, "sinh": 268, "l\u00e0m": 269, "t\u00e1c": 270, "thi": 271, "sau": 272, "nghi\u00eam": 273, "gi\u00e3n": 274, "x\u00e3": 275, "th\u1ecb": 276, "di": 277, "l\u1ecbch": 278, "nhi\u1ec7m": 279, "v\u1ee5": 280, "k\u1ef3": 281, "t\u00e2m": 282, "x\u1ebfp": 283, "chung": 284, "m\u1ed9t": 285, "ng\u1eabu": 286, "nhi\u00ean": 287, "24": 288, "27": 289, "\u0111\u1ee7": 290, "ti\u00eau": 291, "chu\u1ea9n": 292, "kh\u1ecfi": 293, "ch\u1ea9n": 294, "\u0111o\u00e1n": 295, "th\u1ee7": 296, "thu\u1eadt": 297, "ph\u1eabu": 298, "...": 299, "\u0111\u1ed1i": 300, "nh\u01b0": 301, "nghi": 302, "ki\u1ec3m": 303, "so\u00e1t": 304, "t\u1eadt": 305, "g\u1eedi": 306, "v\u1ec7": 307, "t\u1ec5": 308, "h\u00e3ng": 309, "vietnam": 310, "airlines": 311, "18/3": 312, "235": 313, "25": 314, "qu\u1ed1c": 315, "t\u1ecbch": 316, "14/3": 317, "vi\u1ec7c": 318, "m\u1edbi": 319, "374": 320, "381": 321, "t\u1ed5ng": 322, "m\u00f9a": 323, "353": 324, "b\u00ecnh": 325, "chi\u1ebfm": 326, "93%": 327, "pcr": 328, "b\u1ea3y": 329, "k\u1ec3": 330, "h\u1ebft": 331, "h\u1ea1n": 332, "ph\u1ee5": 333, "n\u1eef": 334, "nhi\u1ec1u": 335, "bhutan": 336, "gia": 337, "\u0111\u00ecnh": 338, "b\u1ea1n": 339, "b\u00e8": 340, "th\u1eadm": 341, "ch\u00ed": 342, "mua": 343, "s\u1eafm": 344, "20": 345, "64": 346, "n\u1ed9i": 347, "t\u00e1o": 348, "15/4": 349, "ba": 350, "ph\u1ea7n": 351, "t\u1ef1": 352, "tri\u1ec7u": 353, "ch\u1ee9ng": 354, "ph\u1ed5": 355, "ho": 356, "\u00f4ng": 357, "gi\u00e1m": 358, "s\u00e1t": 359, "nh\u00f3m": 360, "d\u1ef1": 361, "th\u00e1nh": 362, "l\u1ec5": 363, "gi\u00e1o": 364, "malaysia": 365, "170": 366, "b\u1eafc": 367, "giang": 368, "th\u00e1i": 369, "nguy\u00ean": 370, "t\u1eadp": 371, "t\u1eebng": 372, "\u0111\u01b0a": 373, "bu\u1ed5i": 374, "\u0111\u00e0": 375, "n\u1eb5ng": 376, "ho\u00e0": 377, "vang": 378, "b\u1ed1": 379, "b\u1ed1n": 380, "505": 381, "757": 382, "766": 383, "784": 384, "ch\u1ea1y": 385, "t\u1ea1o": 386, "da": 387, "li\u1ec5u": 388, "\u0111\u1ec3": 389, "chu": 390, "h\u00f9ng": 391, "nhanh": 392, "ph\u1ee9c": 393, "t\u1ea1p": 394, "t\u00ecnh": 395, "tr\u1ea1ng": 396, "nguy": 397, "k\u1ecbch": 398, "ph\u1ed5i": 399, "t\u1ed5n": 400, "th\u01b0\u01a1ng": 401, "n\u1eb7ng": 402, "h\u00f4": 403, "h\u1ea5p": 404, "t\u1ea1ng": 405, "m\u1ea1ng": 406, "\u0111e": 407, "do\u1ea1": 408, "f1": 409, "f2": 410, "c\u00fam": 411, "vi\u00eam": 412, "m\u00e3n": 413, "giai": 414, "cu\u1ed1i": 415, "ung": 416, "th\u01b0": 417, "tim": 418, "m\u1ea1ch": 419, "\u2026": 420, "c\u1ed9ng": 421, "nh\u1eadp": 422, "tr\u00e1i": 423, "ph\u00e9p": 424, "to\u00e0n": 425, "7": 426, "nay": 427, "realtime": 428, "c\u00f2n": 429, "l\u1ea1i": 430, "750": 431, "28": 432, "ph\u01b0\u1eddng": 433, "749": 434, "tr\u00ecnh": 435, "gian": 436, "82": 437, "l\u00fac": 438, "81": 439, "f": 440, "34": 441, "v\u1eabn": 442, "b\u1eaft": 443, "\u0111\u1ea7u": 444, "kho\u1ea3ng": 445, "tu\u1ea7n": 446, "m\u1ea5t": 447, "kh\u1ee9u": 448, "gi\u00e1c": 449, "may": 450, "m\u1eafn": 451, "b\u01b0\u1edbc": 452, "\u1ed5n": 453, "m\u00e1y": 454, "t\u1ea1m": 455, "d\u1eebng": 456, "m\u00e1u": 457, "m\u1ee9c": 458, "\u0111\u1ed9": 459, "b\u1edbt": 460, "ngay": 461, "th\u00ec": 462, "129": 463, "ngh\u0129a": 464, "h\u1ecdc": 465, "b\u00e0i": 466, "vn": 467, "0054": 468, "dung": 469, "qu\u1ea5t": 470, "ng\u00e3i": 471, "\u0111\u00e1ng": 472, "ch\u00fa": 473, "\u00fd": 474, "116": 475, "n.x.t.": 476, "n.q.t.": 477, "r\u1ea1ng": 478, "\u0111o\u00e0n": 479, "tr\u01b0\u1edfng": 480, "k\u1ebf": 481, "ho\u1ea1ch": 482, "t\u01b0": 483, "nguy\u1ec5n": 484, "582": 485, "vi\u00ean": 486, "hi\u00ean": 487, "h\u1ea3i": 488, "ch\u00e2u": 489, "31": 490, "l\u00fd": 491, "t\u0103ng": 492, "huy\u1ebft": 493, "\u00e1p": 494, "thi\u1ebfu": 495, "c\u1ee5c": 496, "kha": 497, "malyasia": 498, "\u0111\u1ea1o": 499, "n\u00ean": 500, "r\u00e0": 501, "th\u01b0\u1ee3ng": 502, "l\u01b0u": 503, "nai": 504, "m\u1ecdi": 505, "ngu\u1ed3n": 506, "l\u1ef1c": 507, "l\u0129nh": 508, "v\u1ef1c": 509, "\u1ea3nh": 510, "h\u01b0\u1edfng": 511, "c\u1ea7n": 512, "l\u01b0\u1ee3ng": 513, "\u0111\u1eb7c": 514, "bi\u1ec7t": 515, "l\u00e2y": 516, "ch\u00e9o": 517, "27/6": 518, "kuwait": 519, "xu\u1ea5t": 520, "v\u1eeba": 521, "\u00e2u": 522, "ubnd": 523, "bi\u00ean": 524, "d\u1ee1": 525, "b\u1ecf": 526, "tuy\u1ebfn": 527, "h\u1ed3": 528, "v\u0103n": 529, "\u0111\u1ea1i": 530, "c\u01b0": 531, "tr\u00fa": 532, "595": 533, "669": 534, "phong": 535, "to\u1ea3": 536, "c\u00f4": 537, "s\u1ed1ng": 538, "nh898": 539, "tokyo": 540, "b\u1ea3n": 541, "8/8": 542, "test": 543, "th\u0103m": 544, "ch\u1ecb": 545, "n\u1eb1m": 546, "t\u1ea7ng": 547, "6": 548, "g": 549, "567": 550, "568": 551, "1/4": 552, "nghi\u00ean": 553, "c\u1ee9u": 554, "tra": 555, "phim": 556, "ch\u1ee5p": 557, "x": 558, "quang": 559, "63": 560, "ch\u00f9m": 561, "ti\u00ean": 562, "h\u1ec7": 563, "th\u1ed1ng": 564, "d\u1eef": 565, "li\u1ec7u": 566, "449": 567, "29/7": 568, "tr\u00f9ng": 569, "ti\u1ec3u": 570, "kh\u1edbp": 571, "u\u1ed1ng": 572, "ti\u1ec7m": 573, "ho\u00e1": 574, "23/8": 575, "guinea": 576, "x\u00edch": 577, "s\u00e2n": 578, "vn6": 579, "r\u00f5": 580, "t\u1ed5": 581, "ch\u1ee9c": 582, "\u0111\u0103ng": 583, "k\u00fd": 584, "\u0111\u1ea3m": 585, "b\u1ea3o": 586, "quy": 587, "an": 588, "v\u1eadn": 589, "b\u1eb1ng": 590, "ti\u1ec7n": 591, "thu": 592, "35": 593, "b\u00e1n": 594, "h\u00e0ng": 595, "si\u00eau": 596, "\u0111i\u1ec7n": 597, "h\u1ecd": 598, "5": 599, "12": 600, "271": 601, "sars": 602, "cov": 603, "890": 604, "47": 605, "c\u1ea9m": 606, "l\u1ec7": 607, "877": 608, "878": 609, "879": 610, "880": 611, "khu": 612, "th\u00e1p": 613, "m.": 614, "tr\u1ef1c": 615, "chi\u1ebfn": 616, "cu\u1ed9c": 617, "h\u1ecdp": 618, "b\u00ednh": 619, "ph\u00f3": 620, "ch\u1ee7": 621, "ng\u00e0nh": 622, "n\u0103ng": 623, "truy": 624, "v\u1ebft": 625, "786": 626, "787": 627, "t\u1ed1i": 628, "15/5": 629, "pasteur": 630, "246": 631, "33": 632, "huy\u1ec7n": 633, "y\u00ean": 634, "th\u00e0nh": 635, "ngh\u1ec7": 636, "b\u1ebfp": 637, "moskva": 638, "nga": 639, "22/7": 640, "736": 641, "mi\u1ec1n": 642, "ch\u1ed1t": 643, "ch\u1eb7n": 644, "tr\u1eadt": 645, "xung": 646, "quanh": 647, "714": 648, "tr\u1ea7n": 649, "th\u1ebf": 650, "c\u01b0\u01a1ng": 651, "b\u00ed": 652, "u\u1ef7": 653, "li\u00eam": 654, "mini": 655, "98": 656, "20/3": 657, "l\u00e1i": 658, "xe": 659, "nhung": 660, "ch\u0103m": 661, "nu\u00f4i": 662, "bn": 663, "ph\u1ed1": 664, "c\u1ee9": 665, "6%": 666, "ti\u1ebfn": 667, "b\u00e9o": 668, "ph\u00ec": 669, "ph\u1ea3n": 670, "\u1ee9ng": 671, "mi\u1ec5n": 672, "d\u1ed9i": 673, "r\u1ed1i": 674, "lo\u1ea1n": 675, "\u0111\u1eb7t": 676, "thu\u1ed1c": 677, "11/3": 678, "s\u1ee9c": 679, "kho\u1ebb": 680, "th\u01b0\u1eddng": 681, "s\u1ea1n": 682, "867": 683, "40": 684, "tp.hcm.": 685, "lao": 686, "862": 687, "609": 688, "s\u00f3c": 689, "832": 690, "s\u01a1": 691, "96": 692, "964": 693, "city": 694, "ch\u00f3ng": 695, "c\u1eadn": 696, "k\u1ecbp": 697, "thi\u1ebft": 698, "\u0111o": 699, "h\u1ecfi": 700, "h\u00ecnh": 701, "s\u1ed5": 702, "m\u0169i": 703, "v\u00f9ng": 704, "hay": 705, "793": 706, "v\u00f5": 707, "thi\u00ean": 708, "c\u00e1n": 709, "897": 710, "ch\u1ecdn": 711, "c\u1eadu": 712, "tu": 713, "m\u1eb7t": 714, "n\u1ed7i": 715, "s\u1ee3": 716, "l\u00ean": 717, "g\u1ed3m": 718, "207": 719, "151": 720, "224": 721, "92": 722, "th\u1ea5y": 723, "30%": 724, "sang": 725, "ch\u1ee3": 726, "r\u1eaby": 727, "\u00edt": 728, "tto": 729, "g\u1ed1c": 730, "ti\u1ec1n": 731, "s\u1eed": 732, "h\u00e0n": 733, "t\u01b0\u01a1ng": 734, "58": 735, "26": 736, "15": 737, "d\u00e2n": 738, "13": 739, "278": 740, "b\u1ea1c": 741, "li\u00eau": 742, "9/4": 743, "\u0111\u1eafk": 744, "l\u1eafk": 745, "tr\u00fac": 746, "b\u1ea1ch": 747, "\u0111\u00eam": 748, "6/3": 749, "lu\u1eadn": 750, "\u0111\u1ed1c": 751, "57": 752, "m\u1ef9": 753, "s\u01b0": 754, "v\u1ee3": 755, "450": 756, "46": 757, "m\u1eb9": 758, "ru\u1ed9t": 759, "ch\u00e1u": 760, "phan": 761, "\u0103n": 762, "la\u0300": 763, "5h30": 764, "9": 765, "904": 766, "833": 767, "26/3": 768, "28/3": 769, "vj647": 770, "gh\u1ebf": 771, "32f": 772, "5/3": 773, "t\u00e0u": 774, "tham": 775, "\u0111\u1ea3o": 776, "c\u00e1t": 777, "22h": 778, "xin": 779, "23h55": 780, "t\u1ed1t": 781, "\u0111au": 782, "h\u1ecdng": 783, "tuy": 784, "ki\u1ec7n": 785, "th\u1ea7n": 786, "kinh": 787, ";": 788, "555": 789, "ngo\u1ea1i": 790, "17/1": 791, "l\u01b0\u1ee3t": 792, "trai": 793, "ban": 794, "t\u00ecm": 795, "ph\u00e2n": 796, "x\u01b0\u1edfng": 797, "ty": 798, "gi\u00e0y": 799, "rieker": 800, "nghi\u1ec7p": 801, "ng\u1ecdc": 802, "28/7": 803, "614": 804, "95": 805, "99": 806, "168": 807, "169": 808, "kh\u1ea3": 809, "b\u00ean": 810, "corona": 811, "kh\u00ed": 812, "qu\u1ea3n": 813, "612": 814, "t\u00e2y": 815, "tr\u00e0": 816, ":": 817, "\u0111.t.x.l": 818, "480": 819, "29": 820, "giao": 821, "\u0111\u01a1n": 822, "ph\u1ed1i": 823, "mai": 824, "th\u00f4n": 825, "khay": 826, "1045": 827, "28/8": 828, "\u1ea5n": 829, "6e8679": 830, "ph\u00fa": 831, "th\u1ecd": 832, "ng\u1edd": 833, "23/7": 834, "gi\u1ed1ng": 835, "601": 836, "163": 837, "x\u0103ng": 838, "d\u1ea7u": 839, "i.": 840, "20/7": 841, "25/7": 842, "h\u1ea7u": 843, "440": 844, "41": 845, "45": 846, "d\u1ee5ng": 847, "48": 848, "gi\u1edd": 849, "li\u1ec1n": 850, "k\u1ec1": 851, "50": 852, "149": 853, "v\u1eady": 854, "ta": 855, "949": 856, "1.068": 857, "qu\u1ebf": 858, "khu\u00ea": 859, "72": 860, "l\u1ed9c": 861, "68": 862, "30": 863, "hu\u1ebf": 864, "ng\u1eef": 865, "nhau": 866, "vui": 867, "ch\u01a1i": 868, "kh\u00e1nh": 869, "chi\u1ec3u": 870, "hoa": 871, "l\u01b0": 872, "1017": 873, "24/8": 874, "bi\u1ec3u": 875, "nh\u1eb9": 876, "17/8": 877, "mexico": 878, "n.q.t": 879, "74": 880, "161": 881, "162": 882, "thanh": 883, "5/8": 884, "nh\u00ecn": 885, "c\u00e1nh": 886, "c\u1eeda": 887, "d\u01b0\u1ee1ng": 888, "c\u1ea3m": 889, "c\u0103ng": 890, "th\u1eb3ng": 891, "16/8": 892, "268": 893, "m\u00f4ng": 894, "h\u1ebbo": 895, "l\u00e1nh": 896, "gi\u1edbi": 897, "gi\u00e1p": 898, "686": 899, "510": 900, "t\u01b0\u01a1i": 901, "c\u01b0\u1eddi": 902, "v\u1eaby": 903, "tay": 904, "ch\u00e0o": 905, "27/3": 906, "tr\u00e1nh": 907, "495": 908, "ch\u1ebft": 909, "truy\u1ec1n": 910, "qu\u00e2n": 911, "s\u1ef1": 912, "*": 913, "ch\u00fang": 914, "t\u00f4i": 915, "31/3": 916, "tam": 917, "hi\u1ec7p": 918, "27/1": 919, "ng\u00e3": 920, "150": 921, "t\u00e1": 922, "86": 923, "87": 924, "t.": 925, "n.h.n": 926, "..": 927, "khai": 928, "tr\u1ea1m": 929, "2/8": 930, "7/8": 931, "7/4": 932, "3.300": 933, "321": 934, "322": 935, "44": 936, "39": 937, "nhu\u1eadn": 938, "tr\u01b0a": 939, "e": 940, "18h": 941, "20/8": 942, "r\u00fat": 943, "ecmo": 944, "t\u00edch": 945, "c\u1ef1c": 946, "chuy\u00ean": 947, "ph\u00fat": 948, "h.": 949, "ch\u1ec9nh": 950, "can": 951, "thi\u1ec7p": 952, "x\u1eed": 953, "l\u00e3nh": 954, "36": 955, "l\u00e2m": 956, "ph\u01b0\u1edbc": 957, "thu\u1eadn": 958, "437": 959, "61": 960, "1/8": 961, "19/7": 962, "49": 963, "quy\u1ec1n": 964, "long": 965, "\u0111\u1ec1": 966, "ngh\u1ecb": 967, "tr\u01b0\u01a1ng": 968, "r\u1ed9ng": 969, "4/3": 970, "london": 971, "ng\u00f5": 972, "60": 973, "ai": 974, "gi\u1ea5y": 975, "17h": 976, "370": 977, "419": 978, "15/7": 979, "c\u1ea1nh": 980, "mang": 981, "v\u1ea5n": 982, "kh\u0103n": 983, "\u0111\u1ed9ng": 984, "cung": 985, "69": 986, "\u0111\u00e1i": 987, "th\u00e1o": 988, "type": 989, "lymphoma": 990, "\u1ed1ng": 991, "m\u1edf": 992, "g\u1ecdi": 993, "\u0111\u1ed3": 994, "to\u00e1n": 995, "th\u1ebb": 996, "gan": 997, "m\u1eadt": 998, "e.": 999, "16h40": 1000, "ho\u00e0n": 1001, "911": 1002, "79": 1003, "duy": 1004, "xuy\u00ean": 1005, "722": 1006, "h\u01b0ng": 1007, "m\u00f4i": 1008, "\u0111\u00e0n": 1009, "b\u00f9i": 1010, "280": 1011, "h\u1ed9": 1012, "t\u00e0i": 1013, "x\u1ebf": 1014, "taxi": 1015, "37": 1016, "l\u00f4": 1017, "t\u1ee9c": 1018, "373": 1019, "53": 1020, "389": 1021, "tr\u00e0n": 1022, "m\u00e0ng": 1023, "th\u1ea1ch": 1024, "r\u1ed3i": 1025, "ngh\u1ec9": 1026, "h\u1ed3ng": 1027, "ph\u1ea1m": 1028, "427": 1029, "477": 1030, "56": 1031, "b\u00f9ng": 1032, "s\u00e1u": 1033, "g\u1ea5p": 1034, "\u0111\u1ee3t": 1035, "r\u1ea5t": 1036, "r\u01a1i": 1037, "ch\u1eefa": 1038, "30/7": 1039, "tr\u00e1ch": 1040, "841": 1041, "kh\u1ed1i": 1042, "7/3": 1043, "1034": 1044, "29/8": 1045, "1040": 1046, "b\u1ed3": 1047, "ho\u1ea3": 1048, "t\u00e1ng": 1049, "khan": 1050, "130": 1051, "243": 1052, "h\u1ea1": 1053, "l\u00f4i": 1054, "m\u00ea": 1055, "linh": 1056, "bu\u1ed9c": 1057, "th\u00fac": 1058, "ki\u1ebfm": 1059, "tr\u01b0ng": 1060, "s\u1ebd": 1061, "xem": 1062, "425": 1063, "12/3": 1064, "148": 1065, "ph\u1ecfng": 1066, "4/8": 1067, "9/8": 1068, "12/8": 1069, "14/8": 1070, "t\u1eadn": 1071, "d\u00e3": 1072, "cabin": 1073, "251": 1074, "t\u1ed1": 1075, "d\u00f9": 1076, "minh": 1077, "tuy\u00ean": 1078, "tr\u1ea3i": 1079, "kh\u00e1ng": 1080, "s\u1eb5n": 1081, "13/2": 1082, "d\u1ef1a": 1083, "h\u1ed1c": 1084, "420": 1085, "ph\u1eadn": 1086, "524": 1087, "qu\u00ea": 1088, "ch\u00ednh": 1089, "120": 1090, "11/2": 1091, "1/7": 1092, "m\u1ec7t": 1093, "\u0111\u00e0m": 1094, "\u0111\u1ed9c": 1095, "590": 1096, "517": 1097, "154": 1098, "145": 1099, "n\u00e0o": 1100, "ti\u1ec7c": 1101, "c\u01b0\u1edbi": 1102, "416": 1103, "gi\u1ea3i": 1104, "thao": 1105, "x\u00f3m": 1106, "\u0111\u00e1m": 1107, "gi\u1ed7": 1108, "q.q.t.": 1109, "lo": 1110, "d\u00e2y": 1111, "ng\u1ef1c": 1112, "cdc": 1113, "m\u1ea7m": 1114, "h\u00e0m": 1115, "m\u1eaft": 1116, "\u00e1nh": 1117, "ni\u1ec1m": 1118, "chia": 1119, "s\u1ebb": 1120, "237": 1121, "gene": 1122, "g\u00e2y": 1123, "430": 1124, "tr\u1ebb": 1125, "737": 1126, "nh\u00ec": 1127, "gh\u00e9": 1128, "tu\u00e2n": 1129, "th\u1ecbnh": 1130, "19h30": 1131, "vay": 1132, "nh\u1ec9": 1133, "?": 1134, "quay": 1135, "m\u1eb7c": 1136, "d\u1ecdc": 1137, "ngang": 1138, "su\u1ed1t": 1139, "h\u1eb9n": 1140, "428": 1141, "nh\u1ed3i": 1142, "s\u1ed1c": 1143, "th\u01a1": 1144, "418": 1145, "ch\u1edd": 1146, "khoanh": 1147, "thai": 1148, "l\u00f2ng": 1149, "550": 1150, "13/9": 1151, "1029": 1152, "gi\u00e0": 1153, "13/5": 1154, "vn0062": 1155, "v\u00e2n": 1156, "\u0111\u1ed3n": 1157, "83": 1158, "115": 1159, "czech": 1160, "383": 1161, "lai": 1162, "189": 1163, "0h": 1164, "29/4": 1165, "32": 1166, "325": 1167, "nh\u1edb": 1168, "c\u00fa": 1169, "tho\u1ea1i": 1170, "th\u1eeba": 1171, "th\u0103ng": 1172, "18/8": 1173, "486": 1174, "n\u1ebfu": 1175, "trao": 1176, "\u0111\u1ed5i": 1177, "gi\u1eefa": 1178, "th\u00e1ng": 1179, "83b": 1180, "ki\u1ec7t": 1181, "visa": 1182, "c\u0103n": 1183, "b\u00e9": 1184, "online": 1185, "ti\u1ec1m": 1186, "\u1ea9n": 1187, "b\u1edfi": 1188, "hcdc": 1189, "kh\u1eb3ng": 1190, "t\u1eafc": 1191, "b\u00e0ng": 1192, "ch\u00e2m": 1193, "\u0111\u00e2u": 1194, "\u0111\u1ea5y": 1195, "v\u00ec": 1196, "b\u1ea5t": 1197, "g\u00e1c": 1198, "ch\u1eafn": 1199, "434": 1200, "9h": 1201, "m\u00f4n": 1202, "x\u00e2y": 1203, "d\u1ef1ng": 1204, "ph\u00e1c": 1205, "l\u01b0\u01a1ng": 1206, "\u0111\u1ea7y": 1207, "vn2": 1208, "21/7": 1209, "bv": 1210, "159": 1211, "\u0111\u1ed9i": 1212, "ng\u0169": 1213, "ch\u1ed7": 1214, "tr\u1ecdng": 1215, "592": 1216, "nu\u031b\u0303": 1217, "100": 1218, "tuo\u0302\u0309i": 1219, "xuye\u0302n": 1220, "qua\u0309ng": 1221, "l.": 1222, "qu\u1ea5y": 1223, "kh\u00f3c": 1224, "ch\u1ea3y": 1225, "h\u00fang": 1226, "h\u1eafng": 1227, "kh\u00f2": 1228, "kh\u00e8": 1229, "37,4": 1230, "c": 1231, "b\u00fa": 1232, "quy\u1ebft": 1233, "ch\u00e2n": 1234, "trang": 1235, "nhu": 1236, "t\u1ec9": 1237, "tr\u1ee3": 1238, "lu\u00e2n": 1239, "phi\u00ean": 1240, "m\u1ecfi": 1241, "ng.": 1242, "n\u1eefa": 1243, "kh\u1ea3o": 1244, "d\u1ecb": 1245, "th\u1ea5p": 1246, "nhi": 1247, "9/7": 1248, "26/7": 1249, "n\u00f4n": 1250, "m\u1eeda": 1251, "ng\u1eebng": 1252, "run": 1253, "r\u1ea9y": 1254, "h\u1ea1nh": 1255, "994": 1256, "ho\u1ea1t": 1257, "358": 1258, "302": 1259, "ni\u00ean": 1260, "lan": 1261, "t\u0129nh": 1262, "ch\u00f3t": 1263, "17/7": 1264, "kh\u1edfi": 1265, "25/3": 1266, "88": 1267, "133": 1268, "d\u00e2u": 1269, "\u0111eo": 1270, "kh\u1ea9u": 1271, "\u1ea5y": 1272, "ch\u1ea5n": 1273, "lo\u1ea1i": 1274, "tr\u1eeb": 1275, "42": 1276, "ph\u00fac": 1277, "bu\u00fdt": 1278, "435": 1279, "574": 1280, "227": 1281, "209": 1282, "bangkok": 1283, "146": 1284, "210": 1285, "238": 1286, "73": 1287, "mi\u1ec7n": 1288, "vn54": 1289, "9/3": 1290, "886": 1291, "tri\u1ec3n": 1292, "+": 1293, "326": 1294, "vi\u1ebft": 1295, "ch\u00e1nh": 1296, "566/1.014": 1297, "gi\u00fap": 1298, "t\u1ea3i": 1299, "belarus": 1300, "vn5062": 1301, "855": 1302, "1.629": 1303, "300": 1304, "hi\u1ebfn": 1305, "bao": 1306, "vj1379": 1307, "24a": 1308, "m\u1ea1nh": 1309, "125": 1310, "126": 1311, "152": 1312, "ngh\u0129": 1313, "6/8": 1314, "ng\u00f4": 1315, "ch\u1ecbu": 1316, "tang": 1317, "h\u1ed7": 1318, "b\u1ea7u": 1319, "d\u1ea1": 1320, "n\u1ea1i": 1321, "589": 1322, "\u0111\u1eb7ng": 1323, "lynh": 1324, "c\u1ee7": 1325, "chi": 1326, "\u0111\u00f3ng": 1327, "v\u00ed": 1328, "d\u1ee5": 1329, "t\u1ea5n": 1330, "n.t.t.": 1331, "thu\u00ea": 1332, "sao": 1333, "860": 1334, "593": 1335, "625": 1336, "547": 1337, "715": 1338, "252": 1339, "campuchia": 1340, "8/4": 1341, "m\u1ed9c": 1342, "1010": 1343, "52": 1344, "958": 1345, "tr\u00ec": 1346, "v\u00f2ng": 1347, "ti\u1ebfng": 1348, "m\u1ed7i": 1349, "lo\u00e9t": 1350, "t\u00ec": 1351, "hi\u1ec3n": 1352, "n\u00f3i": 1353, "thu\u1ea7n": 1354, "\u0111an": 1355, "gi\u01b0\u1eddng": 1356, "5h": 1357, "15/3": 1358, "sim": 1359, "l\u1ea1c": 1360, "13/8": 1361, "h\u01b0\u1eddng": 1362, "422": 1363, "ki\u1ebfn": 1364, "324": 1365, "xoay": 1366, "ng\u1ed3i": 1367, "d\u1eady": 1368, "\u0111\u1ee9ng": 1369, "c\u1ee5": 1370, "144": 1371, "v\u00e0i": 1372, "tr\u1ecbnh": 1373, "ph\u1ee7": 1374, "ng\u1ea7m": 1375, "66": 1376, "2020": 1377, "b\u00e0y": 1378, "binh": 1379, "tr\u1eadn": 1380, "v\u1eadt": 1381, "ch\u1ea5t": 1382, "l\u1ea1t": 1383, "brazil": 1384, "0018": 1385, "812": 1386, "b\u1ebfn": 1387, "tre": 1388, "\u0111\u00e0i": 1389, "loan": 1390, "cam": 1391, "ranh": 1392, "vj2849": 1393, "nha": 1394, "r\u1eb1ng": 1395, "\u0111\u00f3n": 1396, "r\u00e0o": 1397, "59": 1398, "602": 1399, "10/8": 1400, "20h30": 1401, "n\u00e2ng": 1402, "\u0111\u0103k": 1403, "l\u0103k": 1404, "vn1915": 1405, "179": 1406, "\u00e1n": 1407, "gh\u00e9p": 1408, "16/3": 1409, "m\u00e3": 1410, "ngh\u1ebdn": 1411, "u": 1412, "\u00e1c": 1413, "ni\u1ec7u": 1414, "n\u0103m": 1415, "l\u1ed1i": 1416, "g\u00ec": 1417, "thu\u1ef5": 1418, "\u0111i\u1ec3n": 1419, "u\u00f4ng": 1420, "t\u00e1m": 1421, "175": 1422, "xanh": 1423, "p\u00f4n": 1424, "452": 1425, "442": 1426, "5/5": 1427, "ireland": 1428, "s\u1ea3n": 1429, "1048": 1430, "r\u1ecba": 1431, "v\u0169ng": 1432, "ph\u00f9": 1433, "l\u1ed7": 1434, "l\u1eddi": 1435, "\u01a1n": 1436, "tuy\u1ec7t": 1437, "v\u1eddi": 1438, "v\u0129nh": 1439, "m\u00ecnh": 1440, "https://tokhaiyte": 1441, "\u0111\u1eddi": 1442, "84": 1443, "199": 1444, "k\u00e9m": 1445, "t\u00fac": 1446, "x\u00e1": 1447, "143": 1448, "k\u00e8m": 1449, "/": 1450, "b.t.h.": 1451, "54": 1452, "hiv": 1453, "l\u1edbp": 1454, "vinh": 1455, "hi\u1ec1n": 1456, "1.600": 1457, "resort": 1458, "622": 1459, "tr\u1ea5n": 1460, "ngh\u1ec1": 1461, "bu\u00f4n": 1462, "14h": 1463, "22/3": 1464, "909": 1465, "519": 1466, "549": 1467, "563": 1468, "564": 1469, "551": 1470, "616": 1471, "436": 1472, "137": 1473, "38": 1474, "khuy\u1ebfn": 1475, "kh\u00edch": 1476, "n\u00eau": 1477, "d\u00f9ng": 1478, "l\u00e2u": 1479, "d\u1ec5": 1480, "ngon": 1481, "vi": 1482, "doanh": 1483, "n.h.n.": 1484, "d.\u0111.p.": 1485, "d\u1ed3n": 1486, "5/14": 1487, "l\u1edbn": 1488, "cai": 1489, "ng\u01b0ng": 1490, "oxy": 1491, "ch\u00fat": 1492, "t\u00ean": 1493, "l.t.q.": 1494, "11/6": 1495, "&": 1496, "grill": 1497, "45.019": 1498, "43.414": 1499, "518": 1500, "792": 1501, "796": 1502, "ti\u1ebft": 1503, "5.000": 1504, "2.291": 1505, "780": 1506, "d": 1507, "\u200btrong": 1508, "to\u00e0": 1509, "ph\u00eda": 1510, "v\u01b0\u1eddn": 1511, "l\u00e0i": 1512, "458": 1513, "tu\u00fd": 1514, "n.t.d": 1515, "b\u00eca": 1516, "v\u1ed7": 1517, "c\u1ed5": 1518, "nhu\u1ebf": 1519, "\u0111\u00fang": 1520, "phu": 1521, "r\u1eddi": 1522, "h\u01b0\u01a1ng": 1523, "h\u1eb1ng": 1524, "124": 1525, "\u00f4t\u00f4": 1526, "nh\u00e1nh": 1527, "c\u00e0": 1528, "ph\u00ea": 1529, "starbucks": 1530, "khu\u1ea9n": 1531, "n\u00e3o": 1532, "nh\u1ecf": 1533, "447": 1534, "\u01b0\u1edbc": 1535, "1000": 1536, "19/8": 1537, "21/3": 1538, "930": 1539, "4/6": 1540, "ch\u1eafc": 1541, "l\u00e0o": 1542, "70": 1543, "huy": 1544, "\u1ee7": 1545, "b\u00f2": 1546, "n.n.l.": 1547, "b\u00e0o": 1548, "xa": 1549, "456": 1550, "178": 1551, "\u0111\u1ed1ng": 1552, "m\u01b0\u1eddi": 1553, "\u0111\u00e1nh": 1554, "gi\u00e1": 1555, "l\u01b0\u1ee3c": 1556, "ch\u1ee7ng": 1557, "su\u1ea5t": 1558, "v\u0169": 1559, "d\u00e3y": 1560, "d\u01b0\u1edbi": 1561, "ng\u1eafn": 1562, "8/6": 1563, "guillain": 1564, "barre": 1565, "vn814": 1566, "siem": 1567, "reap": 1568, "nghe": 1569, "d\u00e0i": 1570, "ch\u1eadm": 1571, "c\u1ea3i": 1572, "thi\u1ec7n": 1573, "k\u00edp": 1574, "c\u00e1": 1575, "chuy\u1ec7n": 1576, "n.t.b.": 1577, "hu\u1ea5n": 1578, "27/7": 1579, "l\u01b0\u1eddng": 1580, "653": 1581, "668": 1582, "93": 1583, "ng\u1ef1": 1584, "mu\u1ed9n": 1585, "330": 1586, "331": 1587, "19/3": 1588, "934": 1589, "774": 1590, "842": 1591, "n.v.v.": 1592, "th\u00f9": 1593, "996": 1594, "ng\u0103n": 1595, "15/8": 1596, "kim": 1597, "b\u1ea3ng": 1598, "hoan": 1599, "t\u00f4n": 1600, "th\u1ea3o": 1601, "\u0111i\u1ec1n": 1602, "18h15": 1603, "5/9": 1604, "s.": 1605, "2/9": 1606, "hie\u0323\u0302n": 1607, "ta\u0323i": 1608, "be\u0323\u0302nh": 1609, "nha\u0302n": 1610, "\u0111u\u031bo\u031b\u0323c": 1611, "ca\u0301ch": 1612, "\u0111ie\u0302\u0300u": 1613, "tri\u0323": 1614, "vie\u0323\u0302n": 1615, "pho\u0302\u0309i": 1616, "\u0111a\u0300": 1617, "na\u0306\u0303ng": 1618, "\ufffc\ufffc": 1619, "200": 1620, "ch\u00f9a": 1621, "14/9": 1622, "formica": 1623, "414": 1624, "387": 1625, "410": 1626, "412": 1627, "395": 1628, "942": 1629, "62": 1630, "ha\u0309i": 1631, "cha\u0302u": 1632, "tie\u0302\u0301p": 1633, "xu\u0301c": 1634, "vo\u031b\u0301i": 1635, "915": 1636, "q": 1637, "d.": 1638, "ch\u1eb7t": 1639, "ch\u1ebd": 1640, "78": 1641, "277": 1642, "282": 1643, "285": 1644, "286": 1645, "b\u01b0\u1edbu": 1646, "th\u1ea1nh": 1647, "t\u1eb7ng": 1648, "c\u01a1m": 1649, "1021": 1650, "1016": 1651, "q.": 1652, "1011": 1653, "kh\u00ea": 1654, "th\u00edch": 1655, "265": 1656, "l\u1ef1": 1657, "c\u01b0\u1eddng": 1658, "v\u1ecfn": 1659, "v\u1eb9n": 1660, "350": 1661, "351": 1662, "352": 1663, "577": 1664, "3/3": 1665, "453": 1666, "758": 1667, "cho\u00e1ng": 1668, "23/3": 1669, "30/3": 1670, "ch\u1ee5c": 1671, "906": 1672, "908": 1673, "su290": 1674, "42c": 1675, "222": 1676, "ch\u1ed1i": 1677, "bus": 1678, "10/4": 1679, "3/8": 1680, "nh\u00e0n": 1681, "pgs.ts": 1682, "tu\u1ef7": 1683, "718": 1684, "hu\u1ed1ng": 1685, "80": 1686, "qu\u1ef3nh": 1687, "719": 1688, "723": 1689, "730": 1690, "51": 1691, "562": 1692, "962": 1693, "xua\u0302n": 1694, "ha\u0300": 1695, "no\u0323\u0302i": 1696, "\u0111e\u0302\u0301n": 1697, "tha\u0300nh": 1698, "pho\u0302\u0301": 1699, "tu\u031b\u0300": 1700, "canteen": 1701, "t\u1ea7n": 1702, "20h": 1703, "ng\u1ee7": 1704, "907": 1705, "t\u01a1": 1706, "107": 1707, "s\u00f4i": 1708, "253": 1709, "ct": 1710, "scanner": 1711, "hi\u1ec3u": 1712, "treo": 1713, "135": 1714, "v\u01b0\u1ee3t": 1715, "836": 1716, "25/8": 1717, "b.": 1718, "vcv": 1719, "h\u00e1n": 1720, "233": 1721, "248": 1722, "r\u00e1t": 1723, "141": 1724, "l\u00e3o": 1725, "tai": 1726, "n\u1ea1n": 1727, "117": 1728, "118": 1729, "coi": 1730, "\u0111\u1ecdc": 1731, "\u0111\u1edbn": 1732, "kh\u00e1": 1733, "th\u1ea9m": 1734, "19h": 1735, "s\u1edbm": 1736, "991": 1737, "th\u1ea7y": 1738, "praha": 1739, "ch": 1740, "istabul": 1741, "th\u1ed5": 1742, "nh\u0129": 1743, "tk": 1744, "1770": 1745, "turkish": 1746, "20b": 1747, "istanbul": 1748, "tk162": 1749, "16k": 1750, "khoang": 1751, "122": 1752, "\u200bng\u00e0y": 1753, "\u0111.t.": 1754, "facebook": 1755, "ch\u1eb1ng": 1756, "ch\u1ecbt": 1757, "hoang": 1758, "438": 1759, "nguy\u1ec7n": 1760, "danielle": 1761, "smith": 1762, "38,3": 1763, "\u00b0c": 1764, "494": 1765, "\u0111\u1eddm": 1766, "xu\u00e2n": 1767, "1.207": 1768, "108": 1769, "bn1030": 1770, "1031": 1771, "v\u01b0\u01a1ng": 1772, "\u1ea3": 1773, "r\u1eadp": 1774, "uae": 1775, "vn5002": 1776, "\u0111\u01b0\u01a1ng": 1777, "10.872": 1778, "r\u00e0ng": 1779, "24/7": 1780, "l.\u0111.n.": 1781, "113": 1782, "m\u1ed1i": 1783, "konpl\u00f4ng": 1784, "kon": 1785, "tum": 1786, "k\u00eau": 1787, "hong": 1788, "kong": 1789, "che": 1790, "mi\u1ec7ng": 1791, "ch\u1ebf": 1792, "canada": 1793, "lo\u1ea1t": 1794, "h\u1ec1": 1795, "\u0111\u1ea5t": 1796, "s\u1ea3ng": 1797, "h\u1eadu": 1798, "pics": 1799, "m\u1ea1i": 1800, "vincom": 1801, "ng\u00f4n": 1802, "s\u1ee9": 1803, "italy": 1804, "c\u1eed": 1805, "857": 1806, "k\u1ef9": 1807, "367": 1808, "368": 1809, "bangladesh": 1810, "3/7": 1811, "228": 1812, "6/9": 1813, "mac": 1814, "elisa": 1815, "834": 1816, "c4": 1817, "\u01b0u": 1818, "h\u1eaft": 1819, "h\u01a1i": 1820, "d\u00e0ng": 1821, "t\u1ea1": 1822, "n\u00fai": 1823, "gi\u1ea3ng": 1824, "1/3": 1825, "p.t.": 1826, "1963": 1827, "ca\u0301c": 1828, "\u0111o\u0302\u0301i": 1829, "tu\u031bo\u031b\u0323ng": 1830, "509": 1831, "488": 1832, "501": 1833, "426": 1834, "ngu\u031bo\u031b\u0300i": 1835, "nha\u0300": 1836, "cha\u0306m": 1837, "so\u0301c": 1838, "o\u031b\u0309": 1839, "qua\u0323\u0302n": 1840, "kha\u0301m": 1841, "ngoa\u0323i": 1842, "tru\u0301": 1843, "443": 1844, "29/3": 1845, "7/9": 1846, "4/9": 1847, "249": 1848, "3/5": 1849, "guilain": 1850, "9/6": 1851, "317": 1852, "m\u1ed1ng": 1853, "philippines": 1854, "n\u00f3ng": 1855, "vanda": 1856, "885": 1857, "n\u1ea1": 1858, "b\u1ed5": 1859, "sung": 1860, "r\u00e9t": 1861, "n\u00e9t": 1862, "vj7816": 1863, "c\u1ed5ng": 1864, "g\u1ee1": 1865, "13/7": 1866, "476": 1867, "507": 1868, "l\u00e2n": 1869, "em": 1870, "13/16": 1871, "873": 1872, "77": 1873, "823": 1874, "th.": 1875, "433": 1876, "\u0111\u00f4": 1877, "\u0111\u1ea1t": 1878, "l\u1ea7u": 1879, "\u0111\u00e8n": 1880, "673": 1881, "674": 1882, "744": 1883, "794": 1884, "2h": 1885, "t\u1ea3": 1886, "d\u00e0nh": 1887, "k\u00ea": 1888, "q.g\u00f2": 1889, "v\u1ea5p": 1890, "933": 1891, "ho\u0323\u0302i": 1892, "c\u1ea5y": 1893, "912": 1894, "thang": 1895, "kh\u1eed": 1896, "thinh": 1897, "8/3": 1898, "320": 1899, "samsung": 1900, "106": 1901, "262": 1902, "tnhh": 1903, "c\u1eedu": 1904, "20/20": 1905, "n\u1eafm": 1906, "h\u01b0u": 1907, "71": 1908, "21/8": 1909, "bu\u1ed3ng": 1910, "tr\u1ee9ng": 1911, "b\u1ee5ng": 1912, "s\u1ecfi": 1913, "c\u1eaft": 1914, "f0": 1915, "2/4": 1916, "ngay\u200b\u200b\u200b\u200b\u200b\u200b": 1917, "th\u1ee9c": 1918, "cu\u1ed1n": 1919, "chi\u1ebfu": 1920, "p.": 1921, "985": 1922, "988": 1923, "65": 1924, "m\u00f4": 1925, "1,134": 1926, "963": 1927, "song": 1928, "761": 1929, "v.h.c.": 1930, "ph\u1edf": 1931, "429": 1932, "499": 1933, "475": 1934, "lam": 1935, "22/8": 1936, "c\u1ed1": 1937, "h\u1ea1ng": 1938, "26/8": 1939, "ng\u1eb7t": 1940, "tu\u1ea5n": 1941, "tu\u1ef3": 1942, "ng\u1ea1t": 1943, "13/3": 1944, "678": 1945, "l\u1ea1ng": 1946, "5/7": 1947, "8h30": 1948, "448": 1949, "s\u00f3t": 1950, "tho\u00e1ng": 1951, "43": 1952, "s\u1eafp": 1953, "tr\u0103m": 1954, "k\u1ef5": 1955, "'": 1956, "d\u1ed1i": 1957, "15h30": 1958, "22/2": 1959, "h\u00e3y": 1960, "nh\u1eb1m": 1961, "vn1": 1962, "314": 1963, "17h30": 1964, "v.": 1965, "h.h.t.": 1966, "\u0111\u1ecf": 1967, "\u00eam": 1968, "1.500": 1969, "800": 1970, "431": 1971, "485": 1972, "166": 1973, "huy\u1ec1n": 1974, "b\u1eefa": 1975, "m\u1ef1c": 1976, "\u0111\u00f2i": 1977, "vn62": 1978, "arkhangelsk": 1979, "hy": 1980, "v\u1ecdng": 1981, "12/7": 1982, "b\u1eedu": 1983, "tr\u1ed1n": 1984, "332": 1985, "157": 1986, "171": 1987, "c\u00e2n": 1988, "cov2": 1989, "h": 1990, "bs": 1991, "kh\u1eafc": 1992, "254": 1993, "r\u1ec3": 1994, "t\u1ed9c": 1995, "kuala": 1996, "lumpur": 1997, "16.000": 1998, "interferon": 1999, "y\u1ebfn": 2000, "hang": 2001, "11/8": 2002, "di\u1ec7u": 2003, "ho\u00e0i": 2004, "mi\u00eau": 2005, "\u00f3i": 2006, "co": 2007, "qu\u1eafp": 2008, "b.t.th.": 2009, "penang": 2010, "airasia": 2011, "ak1502": 2012, "97": 2013, "\u200bt\u1ed1i": 2014, "1037": 2015, "1036": 2016, "27/8": 2017, "scan": 2018, "pha\u0302\u0300n": 2019, "ho\u0302\u0300i": 2020, "phu\u0323c": 2021, "khoa\u0309ng": 2022, "l\u00e1": 2023, "x\u01a1": 2024, "10%": 2025, "3.084": 2026, "2.437": 2027, "647": 2028, "2/7": 2029, "vn0050": 2030, "7h": 2031, "khi\u00eam": 2032, "905": 2033, "tho\u00e1i": 2034, "c\u1ef1u": 2035, "web": 2036, "li\u1ec7t": 2037, "wgme": 2038, "se": 2039, "ga": 2040, "s\u1eaft": 2041, "toa": 2042, "250": 2043, "kuin": 2044, "18/7": 2045, "x\u00e1o": 2046, "tr\u1ed9n": 2047, "g\u1ee3i": 2048, "244": 2049, "c\u00e0ng": 2050, "1068": 2051, "c\u00e1i": 2052, "mau": 2053, "la": 2054, "ph\u01a1i": 2055, "h\u1ed5ng": 2056, "tr\u1ea3": 2057, "vn319": 2058, "m\u1ee5c": 2059, "\u0111\u00edch": 2060, "d\u1eadp": 2061, "484": 2062, "gi\u1ea3n": 2063, "paris": 2064, "labo": 2065, "969": 2066, "24/4": 2067, "t\u00f9ng": 2068, "cu\u0309a": 2069, "me\u0323": 2070, "\u0111\u1ea3n": 2071, "7.200": 2072, "6.650": 2073, "18/6": 2074, "16/6": 2075, "ng\u1ee9a": 2076, "203": 2077, "234": 2078, "khuya": 2079, "tr\u00f9": 2080, "1a": 2081, "ph\u00f3ng": 2082, "699": 2083, "483": 2084, "kh\u1ea3i": 2085, "90%": 2086, "v\u00e0nh": 2087, "132": 2088, "su": 2089, "290": 2090, "763": 2091, "10/3": 2092, "1038": 2093, "219": 2094, "n.": 2095, "872": 2096, "12h": 2097, "31/8": 2098, "v\u1ed1n": 2099, "4/4": 2100, "k\u00ednh": 2101, "m\u00e9t": 2102, "104": 2103, "phu\u031bo\u031b\u0300ng": 2104, "phu\u0301": 2105, "nga\u0303i": 2106, "d\u1eddi": 2107, "t\u00e1ch": 2108, "tinh": 2109, "\u0111.": 2110, "2h30": 2111, "13h": 2112, "\u00f4": 2113, "217": 2114, "24/6": 2115, "l\u1ee5c": 2116, "big": 2117, "v\u00e9": 2118, "th\u1ea5t": 2119, "rai": 2120, "1015": 2121, "phun": 2122, "102": 2123, "10h": 2124, "101": 2125, "l\u1ed9": 2126, "ma": 2127, "thu\u1ed9t": 2128, "saigontourist": 2129, "mu\u1ed1n": 2130, "g\u00f2": 2131, "12.5": 2132, "f3": 2133, "l\u1eafng": 2134, "cd4": 2135, "240": 2136, "2.000": 2137, "6.500": 2138, "b\u1ed1i": 2139, "70%": 2140, "950": 2141, "c\u1ea3ng": 2142, "6/7": 2143, "lu\u1ed3ng": 2144, "5,5": 2145, "tr\u1ea1ch": 2146, "th\u1eafng": 2147, "tg": 2148, "tr\u1ea7m": 2149, "hu\u1ef3nh": 2150, "ti\u1ec5n": 2151, "l\u1ed7i": 2152, "t\u1ecf": 2153, "267": 2154, "257": 2155, "258": 2156, "v\u00f4": 2157, "25/5": 2158, "569": 2159, "r\u0103ng": 2160, "236": 2161, "the": 2162, "coffee": 2163, "house": 2164, "charm": 2165, "spa": 2166, "14/4": 2167, "156": 2168, "241": 2169, "202": 2170, "m\u00f3c": 2171, "467": 2172, "687": 2173, "\u0111\u1ee3i": 2174, "191": 2175, "1022": 2176, "\u0111\u1ebb": 2177, "a": 2178, "h\u00f3c": 2179, "lu\u00f4n": 2180, "1.040": 2181, "ng\u1eeba": 2182, "1.079": 2183, "288": 2184, "nagoya": 2185, "cafe": 2186, "11/5": 2187, "52/54": 2188, "90": 2189, "364": 2190, "527": 2191, "528": 2192, "529": 2193, "530": 2194, "531": 2195, "532": 2196, "533": 2197, "534": 2198, "535": 2199, "538": 2200, "539": 2201, "540": 2202, "541": 2203, "542": 2204, "543": 2205, "545": 2206, "546": 2207, "670": 2208, "457": 2209, "490": 2210, "554": 2211, "584": 2212, "586": 2213, "606": 2214, "633": 2215, "657": 2216, "690": 2217, "694": 2218, "724": 2219, "726": 2220, "732": 2221, "733": 2222, "734": 2223, "735": 2224, "770": 2225, "825": 2226, "643": 2227, "773": 2228, "ph\u00ed": 2229, "ng\u01a1i": 2230, "t\u1eafm": 2231, "bi\u1ec3n": 2232, "\u1ea9m": 2233, "n\u1ed5i": 2234, "\u0111bscl": 2235, "b\u00e0u": 2236, "153": 2237, "p\u00edn": 2238, "t\u1ee7ng": 2239, "cua": 2240, "112": 2241, "vibot": 2242, "men": 2243, "r\u00e1c": 2244, "th\u1ea3i": 2245, "gi\u1eb7t": 2246, "m\u00f9ng": 2247, "b\u00e1nh": 2248, "6h": 2249, "59/165": 2250, "94": 2251, "q.t\u00e2n": 2252, "462": 2253, "tri\u1ec1u": 2254, "2/25": 2255, "6/4": 2256, "ti\u00eam": 2257, "li\u1ec1u": 2258, "bn1032": 2259, "866": 2260, "dixong": 2261, "11h": 2262, "t\u00f4m": 2263, "th\u1ecbt": 2264, "rau": 2265, "23h45": 2266, "0": 2267, "204": 2268, "s\u1ee9ct": 2269, "\u00edch": 2270, "bang": 2271, "l.anh": 2272, "1077": 2273, "th\u1ee3": 2274, "m\u00f3ng": 2275, "t\u01b0\u1edbng": 2276, "29/2": 2277, "tr\u1ee5": 2278, "8/7": 2279, "5/4": 2280, "520": 2281, "c\u0103ngtin": 2282, "620": 2283, "n.v.\u0111.": 2284, "ng\u1eaft": 2285, "qu\u00e3ng": 2286, "daegu": 2287, "201": 2288, "479": 2289, "x\u00e2m": 2290, "oz773": 2291, "so": 2292, "k\u00edn": 2293, "tr\u1eddi": 2294, "16/9": 2295, "gio": 2296, "67/67": 2297, "24/3": 2298, "03126": 2299, "306": 2300, "21h30": 2301, "3h": 2302, "m\u1ea1c": 2303, "amydal": 2304, "m\u00e0u": 2305, "tr\u1eafng": 2306, "ng\u00e0": 2307, "x\u00e1m": 2308, "b\u00f3ng": 2309, "dai": 2310, "d\u00ednh": 2311, "b\u00f3c": 2312, "kh\u00e0n": 2313, "h\u1ea1c": 2314, "g\u00f3c": 2315, "s\u01b0ng": 2316, "to": 2317, "t\u01b0\u1edfng": 2318, "b\u00eanh": 2319, "cha": 2320, "17/3": 2321, "chay": 2322, "sen": 2323, "n\u1ed7": 2324, "s\u1ea1ch": 2325, "l\u1ec7nh": 2326, "eden": 2327, "plaza": 2328, "19h45": 2329, "266": 2330, "ch\u00e1n": 2331, "vn054": 2332, "455": 2333, "571": 2334, "610": 2335, "611": 2336, "712": 2337, "1046": 2338, "thuy\u1ec1n": 2339, "nippon": 2340, "maru": 2341, "h\u1ea1i": 2342, "rung": 2343, "15h": 2344, "684": 2345, "4h30": 2346, "259": 2347, "446": 2348, "398": 2349, "399": 2350, "400": 2351, "401": 2352, "28a": 2353, "gi\u1eef": 2354, "21h": 2355, "ii": 2356, "d\u00e0y": 2357, "medic": 2358, "s\u00e0i": 2359, "g\u00f2n": 2360, "\u1ea5p": 2361, "airfrance": 2362, "af258": 2363, "33h": 2364, "ph\u1ea1t": 2365, "12,5": 2366, "tung": 2367, "uniqlo": 2368, "30/8": 2369, "nh\u00e3": 2370, "fpt": 2371, "22h30": 2372, "b\u1ea1i": 2373, "1.026": 2374, "t\u1ee9": 2375, "346": 2376, "100%": 2377, "m\u1ed1c": 2378, "t\u01b0\u1ee3ng": 2379, "n.t.h.": 2380, "h.t.b.": 2381, "561": 2382, "p.t.b.p.": 2383, "498": 2384, "r\u01b0\u1ee3u": 2385, "nh\u1edd": 2386, "\u0111.t.a.": 2387, "1991": 2388, "827": 2389, "n\u1eeda": 2390, "h\u1eb3n": 2391, "h\u00f4n": 2392, "2.200": 2393, "na": 2394, "r\u00ec": 2395, "k\u1ea1n": 2396, "231": 2397, "n.t.c.": 2398, "v\u00f5ng": 2399, "thpt": 2400, "n\u00f4ng": 2401, "981": 2402, "qr": 2403, "974": 2404, "m\u01b0a": 2405, "ards": 2406, "755": 2407, "1/9": 2408, "sai": 2409, "iran": 2410, "sonde": 2411, "tu\u1ef5": 2412, "tri": 2413, "l\u1ee3i": 2414, "a1": 2415, "481": 2416, "xong": 2417, "arn": 2418, "co\u0301": 2419, "lie\u0302n": 2420, "623": 2421, "624": 2422, "626": 2423, "627": 2424, "951": 2425, "334": 2426, "617": 2427, "903": 2428, "vj7387": 2429, "2016": 2430, "b\u1ebf": 2431, "7.300": 2432, "187": 2433, "721": 2434, "955": 2435, "ca\u0302\u0309m": 2436, "le\u0323\u0302": 2437, "ts.bs": 2438, "993": 2439, "970": 2440, "r\u1ea3i": 2441, "t\u1edd": 2442, "camera": 2443, "b\u1edd": 2444, "\u0111\u1ee1": 2445, "23g": 2446, "hen": 2447, "suy\u1ec5n": 2448, "changi": 2449, "cgh": 2450, "802": 2451, "5k": 2452, "142": 2453, "752": 2454, "76": 2455, "441": 2456, "l\u00e0ng": 2457, "m\u1ea1": 2458, "882": 2459, "212": 2460, "44l": 2461, "392": 2462, "264": 2463, "iii": 2464, "n.g.l.": 2465, "p.t.b": 2466, "fanpage": 2467, "1/5": 2468, "164": 2469, "3k": 2470, "viking": 2471, "cruise": 2472, "899": 2473, "vn50": 2474, "24d": 2475, "18/4": 2476, "20/4": 2477, "21/4": 2478, "22/6": 2479, "5/2": 2480, "226": 2481, "\u0111i\u1ec7p": 2482, "559": 2483, "560": 2484, "vj2432": 2485, "indonesia": 2486, "679": 2487, "io4405": 2488, "11/7": 2489, "b\u1ec9nh": 2490, "vj": 2491, "\u0111\u1ea1p": 2492, "d\u1ee5c": 2493, "1.054": 2494, "957": 2495, "183": 2496, "3/9": 2497, "idris": 2498, "twitter": 2499, "221": 2500, "khang": 2501, "421": 2502, "423": 2503, "424": 2504, "260": 2505, "261": 2506, "263": 2507, "bn428": 2508, "\u2013": 2509, "\u00fat": 2510, "arab": 2511, "l.t.\u0111.": 2512, "p": 2513, "37,6": 2514, "oc": 2515, "chu\u1ed7i": 2516, "870": 2517, "16/5": 2518, "vn88": 2519, "dubai": 2520, "t\u1ed3n": 2521, "17/4": 2522, "g\u1ea5u": 2523, "b\u00f4ng": 2524, "ng\u1ea1i": 2525, "quen": 2526, "sn": 2527, "1993": 2528, "1968": 2529, "1955": 2530, "1983": 2531, "\u0111inh": 2532, "typ": 2533, "18h45": 2534, "aiways": 2535, "qr974": 2536, "g\u00edam": 2537, "th\u00e1c": 2538, "2019": 2539, "g\u1ecdn": 2540, "m\u1ea5y": 2541, "x\u00f4n": 2542, "xao": 2543, "c.": 2544, "597": 2545, "598": 2546, "599": 2547, "600": 2548, "t\u01b0\u1eddng": 2549, "\u200bb\u1ec7nh": 2550, "158": 2551, "16/7": 2552, "kh\u00e2m": 2553, "628": 2554, "642": 2555, "ph\u1ebft": 2556, "466": 2557, "th\u00e1m": 2558, "1065": 2559, "kr\u00f4ng": 2560, "b\u00fak": 2561, "john": 2562, "garth": 2563, "oanh": 2564, "ch\u1ea5m": 2565, "d\u1ee9t": 2566, "d\u00ec": 2567, "x\u1ea3y": 2568, "h\u1eefu": 2569, "khanh": 2570, "corticoid": 2571, "m": 2572, "boa": 2573, "vista": 2574, "tphcm": 2575, "1.000": 2576, "469": 2577, "t.v.d.": 2578, "493": 2579, "703": 2580, "497": 2581, "887": 2582, "465": 2583, "k\u1ebd": 2584, "m\u1edd": 2585, "nh\u1ea1t": 2586, "748": 2587, "s\u1ea7m": 2588, "459": 2589, "fv": 2590, "12h3": 2591, "t\u00e1n": 2592, "th\u1eadt": 2593, "c.p.s.": 2594, "oan": 2595, "729": 2596, "731": 2597, "743": 2598, "5.113": 2599, "kh\u1eafp": 2600, "tu\u00fdp": 2601, "c\u1ee5m": 2602, "333": 2603, "525": 2604, "471": 2605, "553": 2606, "airway": 2607, "114": 2608, "sa": 2609, "pa": 2610, "n\u1ed1i": 2611, "24/5": 2612, "mega": 2613, "7/5": 2614, "26/6": 2615, "b\u00fan": 2616, "th\u1ee5": 2617, "206": 2618, "492": 2619, "b\u00ea": 2620, "thui": 2621, "20/6": 2622, "bo\u0323\u0302": 2623, "te\u0302\u0301": 2624, "ru\u0301t": 2625, "kho\u0309i": 2626, "sa\u0301ch": 2627, "h\u1eb9p": 2628, "186": 2629, "482": 2630, "680": 2631, "1.164": 2632, "937": 2633, "938": 2634, "939": 2635, "17/9": 2636, "nh\u1eafc": 2637, "ph\u00e0n": 2638, "n\u00e0n": 2639, "l\u1ebb": 2640, "qu\u1ea7y": 2641, "i": 2642, "han": 2643, "th\u1edd": 2644, "23d": 2645, "gi\u1eadn": 2646, "chuy\u00ea\u0301n": 2647, "t\u01b0\u0300": 2648, "\u0111\u00ea\u0301n": 2649, "emirates": 2650, "ek30": 2651, "12b": 2652, "ek364": 2653, "7k": 2654, "19/4": 2655, "12/4": 2656, "16/4": 2657, "khu\u00f4n": 2658, "965": 2659, "591": 2660, "460": 2661, "776": 2662, "671": 2663, "672": 2664, "89": 2665, "275": 2666, "432": 2667, "\u00e1i": 2668, "594": 2669, "ho\u00e0nh": 2670, "ek": 2671, "394": 2672, "34j": 2673, "111": 2674, "85": 2675, "ek4": 2676, "72j": 2677, "ek392": 2678, "33j": 2679, "\u00fac": 2680, "245": 2681, "198": 2682, "c\u1edfi": 2683, "bi": 2684, "439": 2685, "s\u00e2u": 2686, "serbia": 2687, "th\u00e9p": 2688, "10/7": 2689, "n.v.t.": 2690, "c\u01a1n": 2691, "t\u1ef5": 2692, "463": 2693, "\u201c": 2694, "\u201d": 2695, "2004": 2696, "l\u1ecdt": 2697, "kao": 2698, "ttyt": 2699, "771": 2700, "bia": 2701, "nh\u1eadu": 2702, "van": 2703, "ph\u1ed3ng": 2704, "c\u1ea3n": 2705, "t\u1ed1c": 2706, "stent": 2707, "t\u00edn": 2708, "pgs": 2709, "thuy\u1ebft": 2710, "r\u1ea7m": 2711, "r\u1ed9": 2712, "fashionista": 2713, "milan": 2714, "\u0111\u1ed7": 2715, "vn272": 2716, "vn607": 2717, "4h": 2718, "l\u00e0n": 2719, "s\u00f3ng": 2720, "2000": 2721, "ki\u1ec1u": 2722, "tuy\u1ec3n": 2723, "ng\u00e2n": 2724, "696": 2725, "k\u1eb9t": 2726, "kho\u00e1": 2727, "4.000": 2728, "guo": 2729, "\u0111\u1ea5u": 2730, "gi\u1ecdt": 2731, "b\u1eafn": 2732, "380": 2733, "10.000": 2734, "tr\u00f4ng": 2735, "52.675": 2736, "x\u1ea1": 2737, "566": 2738, "r\u1ee7i": 2739, "ro": 2740, "ch\u1eb3ng": 2741, "585": 2742, "581": 2743, "638": 2744, "682": 2745, "685": 2746, "665": 2747, "vurs": 2748, "6.000": 2749, "virua": 2750, "1009": 2751, "900": 2752, "bu\u1ed3n": 2753, "hu\u1ec7": 2754, "807": 2755, "922": 2756, "c.a.s.": 2757, "man": 2758, "t\u1ee5t": 2759, "411": 2760, "lui": 2761, "b\u1ecba": 2762, "cha\u0301u": 2763, "thu\u031bo\u031b\u0300ng": 2764, "tr\u00f4i": 2765, "r\u1ec7t": 2766, "14/5": 2767, "tan": 2768, "b\u1ea9m": 2769, "15/2": 2770, "v.d.b.": 2771, "n.t.n.a.": 2772, "m\u1ed5": 2773, "t.a.": 2774, "th\u1eed": 2775, "vi\u1ec5n": 2776, "180/180": 2777, "nadia": 2778, "39,2": 2779, "1.642": 2780, "62,1%": 2781, "883": 2782, "858": 2783, "l\u00edt": 2784, "645": 2785, "445": 2786, "seattle": 2787, "washington": 2788, "eva": 2789, "air": 2790, "br395": 2791, "48a": 2792, "ch\u01b0\u01a1ng": 2793, "935": 2794, "\u0111ie\u0323\u0302n": 2795, "ba\u0300n": 2796, "500": 2797, "23/6": 2798, "208": 2799, "989": 2800, "37,8": 2801, "489": 2802, "464": 2803, "tr\u1ed3ng": 2804, "l\u1eafp": 2805, "ch\u1ee9": 2806, "742": 2807, "604": 2808, "619": 2809, "tr\u1ecd": 2810, "nho": 2811, "d\u1ed1c": 2812, "khuy\u00ean": 2813, "1h30": 2814, "dao": 2815, "m\u1ee7n": 2816, "v\u1ea1n": 2817, "176": 2818, "n.t.h.h.": 2819, "mask": 2820, "l\u1ea5n": 2821, "k\u00edch": 2822, "a.": 2823, "\u00f4xy": 2824, "l\u1ea1": 2825, "932": 2826, "m\u01b0\u1eddng": 2827, "ea": 2828, "h\u1ed7n": 2829, "p.l.v.\u0111": 2830, "s\u1ea5n": 2831, "608": 2832, "p.t.b.t.": 2833, "503": 2834, "h.t.n.": 2835, "1/2": 2836, "qu\u1ea7n": 2837, "t\u1ee5": 2838, "di\u1ec7p": 2839, "xo\u00e0i": 2840, "10/6": 2841, "5a": 2842, "700": 2843, "myanmar": 2844, "thu\u1ef7": 2845, "ipanema": 2846, "kommunarka": 2847, "sp3": 2848, "558": 2849, "461": 2850, "ch\u1ea5p": 2851, "\u0111\u1eadp": 2852, "\u0111\u00e1": 2853, "m\u1eafng": 2854, "ch\u1eedi": 2855, "x\u1ed1i": 2856, "x\u1ea3": 2857, "155": 2858, "phuket": 2859, "s\u1eefa": 2860, "\u1ed1c": 2861, "xi\u00ean": 2862, "n\u01b0\u1edbng": 2863, "ch\u1eb7ng": 2864, "1.023": 2865, "1.029": 2866, "7/6": 2867, "220": 2868, "764": 2869, "d\u1ecbp": 2870, "134": 2871, "185": 2872, "193": 2873, "196": 2874, "849": 2875, "1.057": 2876, "m\u1ed1t": 2877, "928": 2878, "\u00e1": 2879, "40%": 2880, "l\u1ea1nh": 2881, "h.v.\u0111.n.": 2882, "607": 2883, "g\u00e1nh": 2884, "\u00e2n": 2885, "22/53": 2886, "491": 2887, "465/491": 2888, "\u0111\u00e9c": 2889, "795": 2890, "797": 2891, "810": 2892, "30/6": 2893, "751": 2894, "v\u1ea5t": 2895, "v\u1ea3": 2896, "287": 2897, "211": 2898, "11/16": 2899, "q.b\u00ecnh": 2900, "1.300": 2901, "c\u00e2u": 2902, "hi": 2903, "972": 2904, "mumbai": 2905, "952": 2906, "cu\u0300ng": 2907, "for": 2908, "you": 2909, "palace": 2910, "luxury": 2911, "ch\u1ed3m": 2912, "2.973": 2913, "11.077": 2914, "931": 2915, "tho\u1ea3i": 2916, "m\u00e1i": 2917, "138": 2918, "l\u00e1ng": 2919, "latvia": 2920, "1019": 2921, "m.a.t": 2922, "kit": 2923, "t\u00fai": 2924, "c\u1ed9t": 2925, "li": 2926, "\u1edbn": 2927, "grab": 2928, "20/27": 2929, "121": 2930, "844": 2931, "845": 2932, "sapa": 2933, "ths.bs": 2934, "nh\u1ea1y": 2935, "\u0111\u00f4i": 2936, "chinh": 2937, "30/4": 2938, "14/7": 2939, "m\u1ec5": 2940, "310": 2941, "ng\u1ea1ch": 2942, "270": 2943, "977": 2944, "139": 2945, "non": 2946, "b\u00fap": 2947, "v\u00e0ng": 2948, "v.b": 2949, "v.t.\u0111.": 2950, "23h5": 2951, "127": 2952, "\u0111\u1ed5": 2953, "x\u00f4": 2954, "v\u00e9t": 2955, "th\u1ea3": 2956, "g\u00e0": 2957, "\u0111u\u1ed5i": 2958, "ngh\u00ecn": 2959, "478": 2960, "04h55": 2961, "vinmec": 2962, "385": 2963, "396": 2964, "nh\u1ee9c": 2965, "ng\u1eedi": 2966, "m\u00f9i": 2967, "3.000": 2968, "5062": 2969, "internet": 2970, "g\u0169i": 2971, "b\u1edbi": 2972, "t.k.h.": 2973, "1973": 2974, "tranh": 2975, "c\u00e3i": 2976, "mining": 2977, "book": 2978, "230": 2979, "t\u00edm": 2980, "m\u1ee3": 2981, "ana": 2982, "maria": 2983, "892": 2984, "whitmore": 2985, "nga\u0300y": 2986, "ve\u0302\u0300": 2987, "s\u00f4\u0301": 2988, "754": 2989, "gas": 2990, "texiana": 2991, "38,5": 2992, "760": 2993, "789": 2994, "173": 2995, "t\u00f3c": 2996, "x\u1ecbt": 2997, "gold": 2998, "15%": 2999, "l\u1ecfng": 3000, "130.000": 3001, "incheon": 3002, "xq": 3003, "28/2": 3004, "khe\u0302": 3005, "hi\u1ebfm": 3006, "tr\u00f2n": 3007, "xinh": 3008, "\u0111\u01b0\u1ee3": 3009, "ph\u00f4": 3010, "0,5": 3011, "97%": 3012, "451": 3013, "753": 3014, "cx906": 3015, "525/989": 3016, "bs.ckii": 3017, "vn163": 3018, "10h20": 3019, "va\u0300": 3020, "ki\u00ean": 3021, "140": 3022, "c\u0169": 3023, "d\u01b0\u0300ng": 3024, "xu\u00e2\u0301t": 3025, "t": 3026, "587": 3027, "588": 3028, "5h15": 3029, "328": 3030, "936": 3031, "\u0111\u1ed9t": 3032, "ng\u1ed9t": 3033, "336": 3034, "342": 3035, "c\u1ea9n": 3036, "mong": 3037, "manh": 3038, "ti\u1ebfc": 3039, "rra": 3040, "vn223": 3041, "2g": 3042, "347": 3043, "16h": 3044, "m\u01b0\u1edbt": 3045, "b\u1ed7ng": 3046, "ch\u1ed1c": 3047, "d\u01b0\u1eddng": 3048, "496": 3049, "d\u00f2ng": 3050, "919": 3051, "lympho": 3052, "real": 3053, "time": 3054, "th\u1ea1c": 3055, "960": 3056, "n\u1ea5m": 3057, "tie\u0302\u0309u": 3058, "22/4": 3059, "717": 3060, "m\u01b0\u1ee3n": 3061, "894": 3062, "2.700": 3063, "11.000": 3064, "172": 3065, "707": 3066, "vj981": 3067, "d\u1ea1ng": 3068, "x\u1ea5p": 3069, "x\u1ec9": 3070, "tr\u00f2": 3071, "898": 3072, "929": 3073, "565": 3074, "v\u1ec9a": 3075, "h\u00e8": 3076, "b\u01a1m": 3077, "r\u1eeda": 3078, "11h15": 3079, "378": 3080, "\u0111\u1ea9y": 3081, "so\u0302\u0301ng": 3082, "rt": 3083, "98,3%": 3084, "peng": 3085, "1067": 3086, "131": 3087, "d\u01b0": 3088, "x\u00f4i": 3089, "casino": 3090, "g\u00e3y": 3091, "x\u01b0\u01a1ng": 3092, "\u0111\u00f9i": 3093, "pizza": 3094, "t\u00f4ng": 3095, "1026": 3096, "913": 3097, "927": 3098, "\u01b0\u1edbt": 3099, "mi": 3100, "13/20": 3101, "167": 3102, "p.t.t.ng.": 3103, "d.t.t.": 3104, "23/2": 3105, "\u1ed1m": 3106, "397": 3107, "454": 3108, "200m": 3109, "672,722": 3110, "cpap": 3111, "23/4": 3112, "l.t.h": 3113, "m\u01a1": 3114, "ti\u0309nh": 3115, "p.t.t.t.": 3116, "h\u00e3i": 3117, "s\u1eeda": 3118, "557": 3119, "983": 3120, "tr\u01b0\u01a1\u0300ng": 3121, "h\u01a1\u0323p": 3122, "\u0111\u00e2\u0300u": 3123, "1965": 3124, "1.016": 3125, "1h": 3126, "kh\u1ea1c": 3127, "gi\u00e0u": 3128, "boeing": 3129, "329": 3130, "m.t.n.t.": 3131, "177": 3132, "\u0111\u1ea3ng": 3133, "catheter": 3134, "oman": 3135, "harmonia": 3136, "677": 3137, "t\u1ea7m": 3138, "5.100": 3139, "184": 3140, "216": 3141, "vie\u0302n": 3142, "thu\u031b\u0323c": 3143, "ta\u0323\u0302p": 3144, "tho\u031b\u0300i": 3145, "474": 3146, "c\u1ea5m": 3147, "qr977": 3148, "quatar": 3149, "n.t.v": 3150, "605": 3151, "g\u1ee5c": 3152, "g\u1ed1i": 3153, "895": 3154, "t\u1ef1u": 3155, "d\u00e2ng": 3156, "m\u1ed9": 3157, "ni\u1ec7m": 3158, "8h1": 3159, "8h4": 3160, "335": 3161, "c\u00f5i": 3162, "nh\u1eafn": 3163, "n.m.": 3164, "v\u00fa": 3165, "552": 3166, "b\u00f9": 3167, "th\u1eaft": 3168, "l\u01b0ng": 3169, "qr0976": 3170, "37k": 3171, "j": 3172, "2012": 3173, "kg": 3174, "nh\u1ee7": 3175, "g\u1eafn": 3176, "b\u00f3": 3177, "x\u1ee9ng": 3178, "straits": 3179, "times": 3180, "\u0111\u1ec9nh": 3181, "nh": 3182, "294": 3183, "299": 3184, "307": 3185, "311": 3186, "11/9": 3187, "t\u1ebft": 3188, "239": 3189, "km": 3190, "n.t.t.n.": 3191, "888": 3192, "ph\u1ebf": 3193, "b\u1ecdt": 3194, "tr\u00e0ng": 3195, "sigma": 3196, "dinh": 3197, "teo": 3198, "\u0111\u00e9t": 3199, "l\u00e3m": 3200, "621": 3201, "b.\u0111.tr.": 3202, "125,126": 3203, "p.t.m.t.": 3204, "vj826": 3205, "fashion": 3206, "week": 3207, "b\u00e1": 3208, "th\u01b0\u1edbc": 3209, "m\u00e1ch": 3210, "gout": 3211, "1990": 3212, "875": 3213, "24/7/2020": 3214, "quy\u1ebfn": 3215, "luy\u1ebfn": 3216, "572": 3217, "710": 3218, "630": 3219, "881": 3220, "h\u1ed9p": 3221, "it": 3222, "190": 3223, "b\u00e3o": 3224, "cytokine": 3225, "u\u031bo\u031bng": 3226, "vti\u1ebfp": 3227, "\u0111\u00e1n": 3228, "m\u1ec9m": 3229, "ch\u1ee3t": 3230, "b\u1eebng": 3231, "t\u1ea9m": 3232, "li\u1ec7m": 3233, "tr\u00edch": 3234, "gi\u1ecdng": 3235, "duy\u00ean": 3236, "r\u01b0ng": 3237, "video": 3238, "call": 3239, "nh\u1ecdc": 3240, "732,733": 3241, "io": 3242, "4405": 3243, "huflit": 3244, "283": 3245, "canh": 3246, "v\u1ed9i": 3247, "h\u1ec7t": 3248, "pakistan": 3249, "bn321": 3250, "bn322": 3251, "software": 3252, "bo\u0302\u0301": 3253, "\u0111\u1ee9t": 3254, "vnexpress": 3255, "473": 3256, "ceton": 3257, "acid": 3258, "n.t.d.": 3259, "649": 3260, "4/5": 3261, "816": 3262, "2a": 3263, "7h3": 3264, "6/6": 3265, "178/181": 3266, "sui": 3267, "k20": 3268, "b\u00e3i": 3269, "qu\u00fd": 3270, "c\u00e1p": 3271, "ch\u1ea3": 3272, "1.900": 3273, "5h45": 3274, "575": 3275, "a2": 3276, "1025": 3277, "1027": 3278, "\u0111\u1ed5ng": 3279, "n95": 3280, "23h": 3281, "745": 3282, "747": 3283, "0062": 3284, "791": 3285, "thi\u1ec3u": 3286, "\u1ee7ng": 3287, "33d": 3288, "vn340": 3289, "c\u1ea5t": 3290, "1h19": 3291, "h\u00edt": 3292, "khung": 3293, "999": 3294, "775": 3295, "990": 3296, "h\u00f2n": 3297, "gai": 3298, "7.000": 3299, "1.007": 3300, "huddersfield": 3301, "d\u1ea1y": 3302, "987": 3303, "548": 3304, "gs": 3305, "354": 3306, "651": 3307, "273": 3308, "gen": 3309, "1.592": 3310, "10/12": 3311, "68%": 3312, "corana": 3313, "369": 3314, "81%": 3315, "ng\u00e0n": 3316, "h1n1": 3317, "174": 3318, "b\u1ea5m": 3319, "n\u00fat": 3320, "khi\u1ec3n": 3321, "d\u01b0\u1ee3c": 3322, "1.021": 3323, "1.022": 3324, "hi\u1ebfu": 3325, "japan": 3326, "p.v.t.": 3327, "50c": 3328, "jl752": 3329, "23h50": 3330, "narita": 3331, "th\u1ea7m": 3332, "pham": 3333, "m\u1ed3": 3334, "c\u00f4i": 3335, "1032": 3336, "9h30": 3337, "b21": 3338, "\u00e0": 3339, "ch\u1ee9a": 3340, "874": 3341, "k105": 3342, "c\u1ed3n": 3343, "ng\u00f4i": 3344, "nh\u1ed9n": 3345, "nh\u1ecbp": 3346, "phi\u1ebfu": 3347, "508": 3348, "r\u01b0\u1ee1i": 3349, "r\u1eebng": 3350, "\u0111.t.h.": 3351, "rong": 3352, "60%": 3353, "icu": 3354, "sepsis": 3355, "septic": 3356, "shock": 3357, "n\u00e9": 3358, "b\u1ee9c": 3359, "livestream": 3360, "gi\u00f3": 3361, "87.000": 3362, "nh\u1ea7m": 3363, "l\u1eabn": 3364, "1.027": 3365, "1.325": 3366, "343": 3367, "349": 3368, "\u200bchi\u1ec1u": 3369, "713": 3370, "181": 3371, "1.114": 3372, "20%": 3373, "nepal": 3374, "304": 3375, "232": 3376, "gs.ts": 3377, "194": 3378, "205": 3379, "s\u1ef9": 3380, "nh\u1ea3y": 3381, "3/2": 3382, "1.024": 3383, "8/13": 3384, "b\u1ec9": 3385, "30e": 3386, "th\u1ec9nh": 3387, "tho\u1ea3ng": 3388, "a9": 3389, "g\u1eafng": 3390, "n.k.t.": 3391, "s\u00e1nh": 3392, "1956": 3393, "j.b.b": 3394, "j.b.b.": 3395, "n.h.l.": 3396, "m\u00e3i": 3397, "921": 3398, "<pad>": 0, "<unk>": 1}, "pad_token": "<pad>", "pad_token_id": 0, "unk_token": "<unk>", "unk_token_id": 1}